{"chunk_definitions":[{"row":9,"row_count":1,"visible":true,"expansion_state":0,"options":{"engine":"r","label":"setup","include":false},"document_id":"98509DF9","chunk_id":"csetup_chunk","chunk_label":"setup"},{"row":68,"row_count":1,"visible":true,"expansion_state":0,"options":{"engine":"r","warning":false,"label":"unnamed-chunk-29"},"document_id":"98509DF9","chunk_id":"cxk308ak5ksn8","chunk_label":"unnamed-chunk-1"},{"row":75,"row_count":1,"visible":true,"expansion_state":0,"options":{"engine":"r","message":false,"warning":false,"label":"unnamed-chunk-11"},"document_id":"98509DF9","chunk_id":"ciifoiezvxepx","chunk_label":"unnamed-chunk-2"},{"row":102,"row_count":1,"visible":true,"expansion_state":0,"options":{"engine":"r","warning":false,"label":"unnamed-chunk-14"},"document_id":"B240EC9F","chunk_id":"cdewod18hjqo5","chunk_label":"unnamed-chunk-3"},{"row":113,"row_count":1,"visible":true,"expansion_state":0,"options":{"engine":"r","warning":false,"label":"unnamed-chunk-18"},"document_id":"B240EC9F","chunk_id":"cf35cieg0xodi","chunk_label":"unnamed-chunk-4"},{"row":124,"row_count":1,"visible":true,"expansion_state":0,"options":{"engine":"r","warning":false,"label":"unnamed-chunk-19"},"document_id":"B240EC9F","chunk_id":"ct0pkrxjjtisx","chunk_label":"unnamed-chunk-5"},{"row":137,"row_count":1,"visible":true,"expansion_state":0,"options":{"engine":"r","warning":false,"label":"unnamed-chunk-21"},"document_id":"B240EC9F","chunk_id":"c0y47xcqu2v8z","chunk_label":"unnamed-chunk-6"},{"row":156,"row_count":1,"visible":true,"expansion_state":0,"options":{"engine":"r","warning":false,"label":"unnamed-chunk-25"},"document_id":"B240EC9F","chunk_id":"codruiymf6tge","chunk_label":"unnamed-chunk-7"},{"row":186,"row_count":1,"visible":true,"expansion_state":0,"options":{"engine":"r","message":false,"label":"unnamed-chunk-38"},"document_id":"B240EC9F","chunk_id":"cywf8xgwoqln2","chunk_label":"unnamed-chunk-8"}],"doc_write_time":1642469933,"working_dir":null,"default_chunk_options":{"echo":true},"chunk_rendered_width":531}